shttst/files.py
shttst/audio/__init__.py
shttst/audio/audiomentation.py
shttst/audio/tools.py
shttst/audio/utils.py
shttst/dataset/__init__.py
shttst/dataset/dataset_files.py
shttst/dataset/transcription_line.py
shttst/dataset/transcriptions.py
shttst/models/__init__.py
shttst/models/silero_vad.py
shttst/models/speaker_clustering.py
shttst/models/ultimate_vocal_remover.py
shttst/models/vocal_remover.py
shttst/processing/__init__.py
shttst/processing/audio_to_dataset.py
shttst/recipes/__init__.py
shttst/recipes/advanced_split.py
shttst/recipes/auto_speaker_split.py
shttst/recipes/chomik.py
shttst/recipes/multiset.py
shttst/recipes/prepare_tts_wavs.py
shttst/recipes/transcribe_directory.py
shttst/recipes/yt.py
shttst/recipes/yt2.py
shttst/text/__init__.py
shttst/text/shmart_cleaner.py
shttst/text/shmart_nums.py
shttst/text/symbols.py
shttst/text/text.py
shttst-0.1.1.dist-info/LICENSE
shttst-0.1.1.dist-info/METADATA
shttst-0.1.1.dist-info/WHEEL
shttst-0.1.1.dist-info/top_level.txt
shttst-0.1.1.dist-info/RECORD
